MANIFEST.in
README.md
ing.py
requirements.txt
setup.cfg
setup.py
ingdirect/__init__.py
ingdirect/client.py
ingdirect.egg-info/PKG-INFO
ingdirect.egg-info/SOURCES.txt
ingdirect.egg-info/dependency_links.txt
ingdirect.egg-info/requires.txt
ingdirect.egg-info/top_level.txt
ingdirect/images_chiffres_keypad/0.png
ingdirect/images_chiffres_keypad/1.png
ingdirect/images_chiffres_keypad/2.png
ingdirect/images_chiffres_keypad/3.png
ingdirect/images_chiffres_keypad/4.png
ingdirect/images_chiffres_keypad/5.png
ingdirect/images_chiffres_keypad/6.png
ingdirect/images_chiffres_keypad/7.png
ingdirect/images_chiffres_keypad/8.png
ingdirect/images_chiffres_keypad/9.png
test/test_ing.py