Metadata-Version: 1.2
Name: ingdirect
Version: 0.1.0
Summary: Package pour consulter ses comptes bancaires ING Direct
Home-page: https://github.com/tducret/ingdirect-python
Author: Thibault Ducret
Author-email: thibault.ducret@gmail.com
License: MIT
Download-URL: https://github.com/tducret/ingdirect-python/tarball/0.1.0
Keywords: api,banque,ING,ingdirect,comptes
Platform: Posix; MacOS X
Classifier: Programming Language :: Python :: 3
Requires-Python: >=3
